<?xml version='1.0' encoding='utf-8'?>
<TextureAtlas imagePath="horlex.png">
<SubTexture name="horlex idle0000" x="1960" y="0" width="483" height="867" frameX="-336" frameY="-188" frameWidth="1080" frameHeight="1080" />
<SubTexture name="horlex idle0001" x="971" y="1774" width="485" height="862" frameX="-344" frameY="-193" frameWidth="1080" frameHeight="1080" />
<SubTexture name="horlex idle0002" x="1456" y="1774" width="487" height="856" frameX="-353" frameY="-199" frameWidth="1080" frameHeight="1080" />
<SubTexture name="horlex idle0003" x="2431" y="1774" width="485" height="851" frameX="-364" frameY="-204" frameWidth="1080" frameHeight="1080" />
<SubTexture name="horlex idle0004" x="2938" y="0" width="484" height="845" frameX="-376" frameY="-209" frameWidth="1080" frameHeight="1080" />
<SubTexture name="horlex idle0005" x="3422" y="842" width="487" height="840" frameX="-384" frameY="-214" frameWidth="1080" frameHeight="1080" />
<SubTexture name="horlex idle0006" x="3422" y="0" width="488" height="842" frameX="-380" frameY="-212" frameWidth="1080" frameHeight="1080" />
<SubTexture name="horlex idle0007" x="1943" y="1774" width="488" height="856" frameX="-364" frameY="-199" frameWidth="1080" frameHeight="1080" />
<SubTexture name="horlex idle0008" x="2443" y="0" width="495" height="867" frameX="-348" frameY="-188" frameWidth="1080" frameHeight="1080" />
<SubTexture name="horlex idle0009" x="1474" y="0" width="486" height="880" frameX="-332" frameY="-176" frameWidth="1080" frameHeight="1080" />
<SubTexture name="horlex idle0010" x="491" y="0" width="482" height="890" frameX="-310" frameY="-166" frameWidth="1080" frameHeight="1080" />
<SubTexture name="horlex idle0011" x="0" y="0" width="491" height="894" frameX="-292" frameY="-162" frameWidth="1080" frameHeight="1080" />
<SubTexture name="horlex idle0012" x="973" y="0" width="501" height="887" frameX="-286" frameY="-169" frameWidth="1080" frameHeight="1080" />
<SubTexture name="horlex idle0013" x="0" y="894" width="506" height="880" frameX="-283" frameY="-176" frameWidth="1080" frameHeight="1080" />
<SubTexture name="horlex idle0014" x="506" y="894" width="502" height="874" frameX="-298" frameY="-182" frameWidth="1080" frameHeight="1080" />
<SubTexture name="horlex idle0015" x="1008" y="894" width="498" height="868" frameX="-314" frameY="-187" frameWidth="1080" frameHeight="1080" />
<SubTexture name="horlex idle0016" x="2443" y="867" width="492" height="864" frameX="-326" frameY="-191" frameWidth="1080" frameHeight="1080" />
<SubTexture name="horlex idle0017" x="0" y="1774" width="486" height="864" frameX="-334" frameY="-191" frameWidth="1080" frameHeight="1080" />
<SubTexture name="horlex idle0018" x="486" y="1774" width="485" height="864" frameX="-338" frameY="-191" frameWidth="1080" frameHeight="1080" />
</TextureAtlas>
